simple_pass/__init__.py
simple_pass/passwordgen.py
simple_pass/words.txt
simple_pass-1.2.dist-info/entry_points.txt
simple_pass-1.2.dist-info/WHEEL
simple_pass-1.2.dist-info/METADATA
simple_pass-1.2.dist-info/RECORD
