Metadata-Version: 2.1
Name: simple-pass
Version: 1.2
Summary: Secure Password Generator and Checker (uses HaveIBeenPwned)
Home-page: https://github.com/TomFaulkner/simple-password-generation
License: GPL-3.0+
Keywords: passwords,security
Author: Tom Faulkner
Author-email: tomfaulkner@gmail.com
Requires-Python: >=3.6,<4.0
Classifier: License :: OSI Approved :: GNU General Public License v3 or later (GPLv3+)
Classifier: Programming Language :: Python :: 3
Classifier: Programming Language :: Python :: 3.10
Classifier: Programming Language :: Python :: 3.6
Classifier: Programming Language :: Python :: 3.7
Classifier: Programming Language :: Python :: 3.8
Classifier: Programming Language :: Python :: 3.9
Requires-Dist: requests (>=2.21,<3.0)
Project-URL: Repository, https://github.com/TomFaulkner/simple-password-generation
